<?xml version="1.0" encoding="UTF-8"?>
<DARoots Version="1" Minor="26">
  <FileSet Name="constrs_1" Type="Constrs" RelSrcDir="$PSRCDIR/constrs_1">
    <Filter Type="Constrs"/>
    <File Path="$PPRDIR/../TopLevel.ucf">
      <FileInfo>
        <Attr Name="UsedInSynthesis" Val="1"/>
        <Attr Name="UsedInImplementation" Val="1"/>
      </FileInfo>
    </File>
    <File Path="$PPRDIR/../ipcore_dir/city0.ncf">
      <FileInfo>
        <Attr Name="UsedInImplementation" Val="1"/>
      </FileInfo>
    </File>
    <File Path="$PPRDIR/../ipcore_dir/city1.ncf">
      <FileInfo>
        <Attr Name="UsedInImplementation" Val="1"/>
      </FileInfo>
    </File>
    <File Path="$PPRDIR/../ipcore_dir/city2.ncf">
      <FileInfo>
        <Attr Name="UsedInImplementation" Val="1"/>
      </FileInfo>
    </File>
    <File Path="$PPRDIR/../ipcore_dir/city3.ncf">
      <FileInfo>
        <Attr Name="UsedInImplementation" Val="1"/>
      </FileInfo>
    </File>
    <File Path="$PPRDIR/../ipcore_dir/city4.ncf">
      <FileInfo>
        <Attr Name="UsedInImplementation" Val="1"/>
      </FileInfo>
    </File>
    <File Path="$PPRDIR/../ipcore_dir/city5.ncf">
      <FileInfo>
        <Attr Name="UsedInImplementation" Val="1"/>
      </FileInfo>
    </File>
    <File Path="$PPRDIR/../ipcore_dir/city6.ncf">
      <FileInfo>
        <Attr Name="UsedInImplementation" Val="1"/>
      </FileInfo>
    </File>
    <File Path="$PPRDIR/../ipcore_dir/city7.ncf">
      <FileInfo>
        <Attr Name="UsedInImplementation" Val="1"/>
      </FileInfo>
    </File>
    <File Path="$PPRDIR/../ipcore_dir/finch.ncf">
      <FileInfo>
        <Attr Name="UsedInImplementation" Val="1"/>
      </FileInfo>
    </File>
    <File Path="$PDATADIR/constrs_1/designprops.xml">
      <FileInfo SFType="CompatPartsDb"/>
    </File>
    <File Path="$PDATADIR/constrs_1/usercols.xml">
      <FileInfo SFType="UserColsDb"/>
    </File>
    <Config>
      <Option Name="TargetConstrsFile" Val="$PPRDIR/../TopLevel.ucf"/>
      <Option Name="ConstrsType" Val="UCF"/>
    </Config>
  </FileSet>
</DARoots>
